rktellolib/Tello.py
rktellolib/TelloCam.py
rktellolib/TelloCommand.py
rktellolib/TelloState.py
rktellolib/__init__.py
rktellolib-1.0.4.dist-info/METADATA
rktellolib-1.0.4.dist-info/WHEEL
rktellolib-1.0.4.dist-info/top_level.txt
rktellolib-1.0.4.dist-info/RECORD
