Metadata-Version: 2.1
Name: rktellolib
Version: 1.0.4
Summary: A simple library to interface with the DJI Tello drone
Author-email: Ramsin Khoshabeh <ramsin@ucsd.edu>
License: Copyright 2021 Ramsin Khoshabeh, PhD
Project-URL: Homepage, https://github.com/ramujin/rktellolib
Project-URL: Bug Tracker, https://github.com/ramujin/rktellolib/issues
Keywords: dji,tello,ryze,drone,sdk,official sdk
Classifier: Development Status :: 5 - Production/Stable
Classifier: Intended Audience :: Developers
Classifier: Topic :: Software Development :: Build Tools
Classifier: License :: OSI Approved :: MIT License
Classifier: Programming Language :: Python :: 3
Requires-Python: >=3.5
Requires-Dist: opencv-python
Requires-Dist: numpy
